LICENSE
README.md
setup.cfg
setup.py
brawlpy/API.py
brawlpy/__init__.py
brawlpy/errors.py
brawlpy/icons.py
brawlpy/main.py
brawlpy/objects.py
brawlpy/utils.py
brawlpy.egg-info/PKG-INFO
brawlpy.egg-info/SOURCES.txt
brawlpy.egg-info/dependency_links.txt
brawlpy.egg-info/requires.txt
brawlpy.egg-info/top_level.txt