Metadata-Version: 2.1
Name: brawlpy
Version: 1.2.5
Summary: A Basic wrapper for the Brawl Stars API
Home-page: https://github.com/PyStarr/BrawlPy
Author: PyStarr
Author-email: pystarrorg@gmail.com
License: MIT
Download-URL: https://github.com/PyStarr/BrawlPy/archive/v1.2.5.tar.gz
Keywords: wrapper,brawlstars,api,brawlstarsApiWrapper
Platform: UNKNOWN
Classifier: Development Status :: 5 - Production/Stable
Classifier: Intended Audience :: Developers
Classifier: License :: OSI Approved :: MIT License
License-File: LICENSE
